Metadata-Version: 2.1
Name: pydoli
Version: 0.2
Summary: A simple todo list app for the command line
Home-page: https://github.com/linyers/pydoli
Author: Linyers
Author-email: linyers666@gmail.com
License: MIT
Classifier: Programming Language :: Python :: 3
Classifier: License :: OSI Approved :: MIT License
License-File: LICENSE
